{
  "_class": "group",
  "booleanOperation": 0,
  "clippingMaskMode": 0,
  "do_objectID": "A4FE970D-F9D0-4D8D-B440-AE2F39089FF8",
  "exportOptions": {
    "_class": "exportOptions",
    "do_objectID": "0E643114-DFA6-49BD-BF49-80DD24564FB7",
    "exportFormats": [
    ],
    "includedLayerIds": [
    ],
    "layerOptions": 0,
    "shouldTrim": false
  },
  "frame": {
    "_class": "rect",
    "constrainProportions": false,
    "do_objectID": "8406E0A6-7469-4C4D-9E17-82A17AD3B259",
    "height": 80,
    "width": 360,
    "x": 0,
    "y": 0
  },
  "groupLayout": {
    "_class": "MSImmutableFreeformGroupLayout",
    "do_objectID": "F4E61D45-17EE-4163-902D-58C44B4D01B0"
  },
  "hasClickThrough": false,
  "hasClippingMask": false,
  "isFixedToViewport": false,
  "isFlippedHorizontal": false,
  "isFlippedVertical": false,
  "isLocked": false,
  "isVisible": true,
  "layerListExpandedType": 2,
  "layers": [
    {
      "class": "group",
      "id": "BA0E50A2-0365-4A26-9A8A-FA489467CC12"
    },
    {
      "class": "group",
      "id": "A1A6B9A2-036B-46D8-B90C-16BC4EC26D03"
    }
  ],
  "name": "#1",
  "nameIsFixed": true,
  "resizingConstraint": 63,
  "resizingType": 0,
  "rotation": 0,
  "shouldBreakMaskChain": false,
  "style": {
    "_class": "style",
    "do_objectID": "942A9B2C-224F-4A05-B73E-433742F9E294",
    "endMarkerType": 0,
    "miterLimit": 10,
    "startMarkerType": 0,
    "windingRule": 1
  },
  "userInfo": {
    "com.animaapp.stc-sketch-plugin": {
      "kModelPropertiesKey": {
      }
    }
  }
}